thst/__init__.py
thslt-1.0.2.dist-info/LICENSE.txt
thslt-1.0.2.dist-info/METADATA
thslt-1.0.2.dist-info/WHEEL
thslt-1.0.2.dist-info/top_level.txt
thslt-1.0.2.dist-info/RECORD
