Metadata-Version: 2.1
Name: thslt
Version: 1.0.2
Summary: A Thai sign language translator library used with Mediapipe that translate Thai hand sign language into plain Thai characters. 
Author: Papangkon Ninarundech
Author-email: papangkonsk@gmail.com
Classifier: Development Status :: 4 - Beta
Classifier: License :: OSI Approved :: MIT License
Classifier: Operating System :: OS Independent
Requires-Python: >=3.6
License-File: LICENSE.txt
